topsis_rohit_102203804/__init__.py
topsis_rohit_102203804/topsis.py
Topsis_Rohit_102203804-1.2.0.dist-info/LICENSE
Topsis_Rohit_102203804-1.2.0.dist-info/METADATA
Topsis_Rohit_102203804-1.2.0.dist-info/WHEEL
Topsis_Rohit_102203804-1.2.0.dist-info/entry_points.txt
Topsis_Rohit_102203804-1.2.0.dist-info/top_level.txt
Topsis_Rohit_102203804-1.2.0.dist-info/RECORD
