Metadata-Version: 2.1
Name: Topsis-Rohit-102203804
Version: 1.2.0
Summary: Implementation of TOPSIS for multi-criteria decision making
Home-page: https://github.com/therohitsingla/Topsis
Author: Rohit Singla
Author-email: rsingla_be22@thapar.edu
Classifier: Programming Language :: Python :: 3
Classifier: License :: OSI Approved :: MIT License
Classifier: Operating System :: OS Independent
Requires-Python: >=3.6
License-File: LICENSE
Requires-Dist: numpy>=1.19.5
Requires-Dist: pandas>=1.1.5
